piplet/__init__.py
piplet-0.2.0.dist-info/METADATA
piplet-0.2.0.dist-info/WHEEL
piplet-0.2.0.dist-info/entry_points.txt
piplet-0.2.0.dist-info/licenses/LICENSE
piplet-0.2.0.dist-info/RECORD
